clover/__init__.py
clover/__main__.py
clover/__utils__.py
clover/analysis.py
clover/argparser.py
clover/fileparser.py
clover/printer.py
clover/conversion/__init__.py
clover/conversion/conversion.py
clover/conversion/tests/__init__.py
clover/conversion/tests/unit/__init__.py
clover/generation/__init__.py
clover/generation/__utils__.py
clover/generation/solar.py
clover/generation/weather.py
clover/generation/wind.py
clover/generation/tests/__init__.py
clover/generation/tests/component/__init__.py
clover/generation/tests/unit/__init__.py
clover/impact/__init__.py
clover/impact/__utils__.py
clover/impact/finance.py
clover/impact/ghgs.py
clover/impact/tests/__init__.py
clover/impact/tests/component/__init__.py
clover/impact/tests/unit/__init__.py
clover/load/__init__.py
clover/load/load.py
clover/load/tests/__init__.py
clover/load/tests/component/__init__.py
clover/mains_supply/__init__.py
clover/mains_supply/__utils__.py
clover/mains_supply/grid.py
clover/mains_supply/water_source.py
clover/mains_supply/tests/__init__.py
clover/mains_supply/tests/component/__init__.py
clover/mains_supply/tests/unit/__init__.py
clover/optimisation/__init__.py
clover/optimisation/__utils__.py
clover/optimisation/appraisal.py
clover/optimisation/optimisation.py
clover/optimisation/single_line_simulation.py
clover/optimisation/tests/__init__.py
clover/optimisation/tests/component/__init__.py
clover/optimisation/tests/unit/__init__.py
clover/scripts/__init__.py
clover/scripts/clover.py
clover/scripts/clover_hpc_clover.py
clover/scripts/clover_hpc_outbox_assembly.py
clover/scripts/clover_new_location.py
clover/scripts/clover_update_api_token.py
clover/scripts/hpc.py
clover/scripts/hpc_clover.py
clover/scripts/hpc_outbox_assembly.py
clover/scripts/hpc_utils.py
clover/scripts/new_location.py
clover/scripts/update_api_token.py
clover/scripts/tests/__init__.py
clover/scripts/tests/unit/__init__.py
clover/simulation/__init__.py
clover/simulation/__utils__.py
clover/simulation/diesel.py
clover_energy-5.1.1.dist-info/LICENSE
clover_energy-5.1.1.dist-info/METADATA
clover_energy-5.1.1.dist-info/WHEEL
clover_energy-5.1.1.dist-info/entry_points.txt
clover_energy-5.1.1.dist-info/top_level.txt
clover_energy-5.1.1.dist-info/RECORD
