Metadata-Version: 2.1
Name: clover-energy
Version: 5.1.1
Summary: Continuous Lifetime Optimisation of Variable Electricity Resources
Home-page: https://github.com/CLOVER-energy/CLOVER
Author: Phil Sandwell, Ben Winchester and Hamish Beath
Author-email: philip.sandwell@gmail.com,benedict.winchester@gmail.com,hamishbeath@outlook.com
Project-URL: Bug Tracker, https://github.com/CLOVER-energy/CLOVER/issues
Classifier: Programming Language :: Python :: 3.7
Classifier: License :: OSI Approved :: MIT License
Classifier: Operating System :: OS Independent
Requires-Python: >=3.7
License-File: LICENSE
Requires-Dist: numpy (>=1.20.1)
Requires-Dist: pandas (>=1.2.3)
Requires-Dist: PyYAML (>=5.4.1)
Requires-Dist: requests (>=2.25.1)
Requires-Dist: seaborn (>=0.11.1)
Requires-Dist: scikit-learn (>=1.0)
Requires-Dist: scipy (>=1.6.2)
Requires-Dist: tqdm (>=4.59.0)
